bayesian_lora/__init__.py
bayesian_lora/kfac.py
bayesian_lora/main.py
bayesian_lora-0.0.6.dist-info/LICENSE
bayesian_lora-0.0.6.dist-info/METADATA
bayesian_lora-0.0.6.dist-info/WHEEL
bayesian_lora-0.0.6.dist-info/top_level.txt
bayesian_lora-0.0.6.dist-info/RECORD
